pyoes/__init__.py
pyoes/static_views.py
pyoes/utils.py
pyoes/views.py
pyoes/scaffolds/__init__.py
pyoes/scaffolds/pyoes_admin_scaffold/+package+/static/admin/package.json_tmpl
pyoes/scaffolds/pyoes_admin_scaffold/+package+/static/admin/src/app/resources/img/pyoes/OE-vlaanderen-logo.png
pyoes/scaffolds/pyoes_admin_scaffold/+package+/static/admin/src/app/resources/img/pyoes/header-img.jpg
pyoes/scaffolds/pyoes_admin_scaffold/+package+/static/admin/src/app/resources/img/pyoes/header-logo-bg.png
pyoes/scaffolds/pyoes_admin_scaffold/+package+/static/admin/src/app/resources/scss/_+package+.scss_tmpl
pyoes/scaffolds/pyoes_admin_scaffold/+package+/static/admin/src/app/resources/scss/app.scss_tmpl
pyoes/scaffolds/pyoes_proces_scaffold/proces/+package+/readme.txt
pyoes/scaffolds/pyoes_proces_scaffold/proces/+package+/static/admin/package.json_tmpl
pyoes/scaffolds/pyoes_proces_scaffold/proces/+package+/static/admin/src/app/resources/img/pyoes/OE-vlaanderen-logo.png
pyoes/scaffolds/pyoes_proces_scaffold/proces/+package+/static/admin/src/app/resources/img/pyoes/header-img.jpg
pyoes/scaffolds/pyoes_proces_scaffold/proces/+package+/static/admin/src/app/resources/img/pyoes/header-logo-bg.png
pyoes/scaffolds/pyoes_proces_scaffold/proces/+package+/static/admin/src/app/resources/scss/_+package+.scss_tmpl
pyoes/scaffolds/pyoes_proces_scaffold/proces/+package+/static/admin/src/app/resources/scss/app.scss_tmpl
pyoes/scaffolds/pyoes_scaffold/+package+/static/package.json_tmpl
pyoes/scaffolds/pyoes_scaffold/+package+/static/robots.txt
pyoes/scaffolds/pyoes_scaffold/+package+/static/img/pyoes/OE-vlaanderen-logo.png
pyoes/scaffolds/pyoes_scaffold/+package+/static/img/pyoes/header-img.jpg
pyoes/scaffolds/pyoes_scaffold/+package+/static/img/pyoes/header-logo-bg.png
pyoes/scaffolds/pyoes_scaffold/+package+/static/js/app.js
pyoes/scaffolds/pyoes_scaffold/+package+/static/scss/_+package+.scss_tmpl
pyoes/scaffolds/pyoes_scaffold/+package+/static/scss/app.scss_tmpl
pyoes-0.25.0.dist-info/METADATA
pyoes-0.25.0.dist-info/WHEEL
pyoes-0.25.0.dist-info/entry_points.txt
pyoes-0.25.0.dist-info/RECORD
