Metadata-Version: 2.3
Name: pyoes
Version: 0.25.0
Summary: pyoes
Author-email: Flanders Heritage Agency <ict@onroerenderfgoed.be>
Keywords: compass,css,jinja2,pyramid,sass,style,templates
Classifier: Framework :: Pyramid
Classifier: Programming Language :: Python
Requires-Python: <=3.13,>=3.10
Requires-Dist: jinja2==3.1.4
Requires-Dist: markupsafe==2.1.3
Requires-Dist: pyramid-jinja2==2.10
Requires-Dist: pyramid==2.0.2
Requires-Dist: python-dateutil==2.8.2
Provides-Extra: dev
Requires-Dist: coveralls==3.3.1; extra == 'dev'
Requires-Dist: oe-sphinx-theme==0.4.0; extra == 'dev'
Requires-Dist: pep8==1.7.1; extra == 'dev'
Requires-Dist: pytest-cov==4.1.0; extra == 'dev'
Requires-Dist: pytest==7.4.3; extra == 'dev'
Requires-Dist: sphinx-rtd-theme==2.0.0; extra == 'dev'
Requires-Dist: sphinx==7.1.2; extra == 'dev'
Requires-Dist: sphinxcontrib-httpdomain==1.8.1; extra == 'dev'
Requires-Dist: sphinxcontrib-plantuml==0.27; extra == 'dev'
Requires-Dist: waitress==2.1.2; extra == 'dev'
